model/BiLSTM_Attn.py
model/__init__.py
model/bj_BiLSTM_Attn.py
myner_chencheng-0.1.0.dist-info/METADATA
myner_chencheng-0.1.0.dist-info/WHEEL
myner_chencheng-0.1.0.dist-info/top_level.txt
myner_chencheng-0.1.0.dist-info/RECORD
