Metadata-Version: 2.4
Name: myner_chencheng
Version: 0.1.0
Summary: A simple NER package for learning
Author-email: Chen Cheng <your_email@example.com>
License-Expression: MIT
Project-URL: Homepage, https://github.com/yourusername/myner
Requires-Python: >=3.8
Requires-Dist: torch>=1.13
Requires-Dist: transformers>=4.20
